LICENSE.txt
README.md
setup.py
reconciliation/__init__.py
reconciliation/reconcile.py
reconciliation.egg-info/PKG-INFO
reconciliation.egg-info/SOURCES.txt
reconciliation.egg-info/dependency_links.txt
reconciliation.egg-info/requires.txt
reconciliation.egg-info/top_level.txt