Metadata-Version: 2.1
Name: reconciliation
Version: 0.3
Summary: An OpenRefine Reconciliation Framework for Python
Home-page: https://github.com/preftech/reconciliation
Author: patrick oleary
Author-email: techops@preftech.com
License: MIT
Keywords: reconcile,reconciliation,openrefine,cocoda
Platform: UNKNOWN
Classifier: Development Status :: 4 - Beta
Classifier: Intended Audience :: Developers
Classifier: Topic :: Text Processing
Classifier: Framework :: Flask
Classifier: License :: OSI Approved :: MIT License
Classifier: Programming Language :: Python :: 3.6
Classifier: Programming Language :: Python :: 3.7
Classifier: Programming Language :: Python :: 3.8
License-File: LICENSE.txt
